uvisaurorae/__init__.py
uvisaurorae/calibration.py
uvisaurorae/data_retrieval.py
uvisaurorae/executions.py
uvisaurorae/inout.py
uvisaurorae/plotting.py
uvisaurorae/projection.py
uvisaurorae/resources/__init__.py
uvisaurorae/resources/BODY698_SATURN_AURORAL_LAYER.tpc
uvisaurorae/resources/calibration_files/FLATFIELD_FUV_POSTBURN.txt
uvisaurorae/resources/calibration_files/FLATFIELD_FUV_PREBURN.txt
uvisaurorae/resources/calibration_files/FUV_1999_Lab_Cal.dat
uvisaurorae/resources/calibration_files/FUV_CALIBRATION_TIME_EVOLUTION_PARAMETERS.DAT
uvisaurorae/resources/calibration_files/spica_variability4_data.sav
uvisaurorae/resources/calibration_files/UVIS_flat-field_modifiers_2016-01-13/EUV2002_198_11_05_50_UVIS_C33ST_SPICARAST002_PRIME_ff_modifier_1405596163.dat
uvisaurorae/resources/calibration_files/UVIS_flat-field_modifiers_2016-01-13/EUV2003_139_22_53_02_UVIS_C37ST_SPICARAST001_PRIME_T_ff_modifier_1432077170.dat
uvisaurorae/resources/calibration_files/UVIS_flat-field_modifiers_2016-01-13/EUV2005_295_23_51_49_UVIS_017ST_ALPVIR001_PRIME_ff_modifier_1508718035.dat
uvisaurorae/resources/calibration_files/UVIS_flat-field_modifiers_2016-01-13/EUV2006_240_00_45_15_UVIS_027IC_ALPVIR001_PRIME_ff_modifier_1535419007.dat
uvisaurorae/resources/calibration_files/UVIS_flat-field_modifiers_2016-01-13/EUV2007_077_09_40_34_UVIS_041IC_ALPVIR001_PRIME_ff_modifier_1552904039.dat
uvisaurorae/resources/calibration_files/UVIS_flat-field_modifiers_2016-01-13/EUV2007_140_16_20_53_UVIS_045IC_ALPVIR001_PRIME_ff_modifier_1558371293.dat
uvisaurorae/resources/calibration_files/UVIS_flat-field_modifiers_2016-01-13/EUV2007_223_01_45_33_UVIS_049IC_ALPVIR001_PRIME_ff_modifier_1565490018.dat
uvisaurorae/resources/calibration_files/UVIS_flat-field_modifiers_2016-01-13/EUV2007_259_22_47_23_UVIS_050IC_ALPVIR001_PRIME_ff_modifier_1568676148.dat
uvisaurorae/resources/calibration_files/UVIS_flat-field_modifiers_2016-01-13/EUV2007_332_03_09_38_UVIS_053IC_ALPVIR001_PRIME_ff_modifier_1574912726.dat
uvisaurorae-0.1.2.dist-info/LICENSE
uvisaurorae-0.1.2.dist-info/WHEEL
uvisaurorae-0.1.2.dist-info/METADATA
uvisaurorae-0.1.2.dist-info/RECORD
